haf/__init__.py
haf/__main__.py
haf/apihelper.py
haf/apphelper.py
haf/asserthelper.py
haf/bench.py
haf/bus.py
haf/busclient.py
haf/case.py
haf/config.py
haf/globalenv.py
haf/helper.py
haf/hookspecs.py
haf/lib.py
haf/loader.py
haf/logger.py
haf/main.py
haf/mark.py
haf/message.py
haf/pluginmanager.py
haf/program.py
haf/recorder.py
haf/result.py
haf/runner.py
haf/signal.py
haf/suite.py
haf/utils.py
haf/webhelper.py
haf/common/__init__.py
haf/common/database.py
haf/common/exception.py
haf/common/httprequest.py
haf/common/lock.py
haf/common/log.py
haf/common/schema.py
haf/common/sigleton.py
haf/common/__pycache__/__init__.cpython-37.pyc
haf/common/__pycache__/database.cpython-37.pyc
haf/common/__pycache__/exception.cpython-37.pyc
haf/common/__pycache__/httprequest.cpython-37.pyc
haf/common/__pycache__/log.cpython-37.pyc
haf/common/__pycache__/schema.cpython-37.pyc
haf/common/__pycache__/sigleton.cpython-37.pyc
haf/ext/__init__.py
haf/ext/jinjia2report/report.py
haf/ext/jinjia2report/__pycache__/report.cpython-37.pyc
haf/ext/resource/report/base.css
haf/ext/resource/report/base.html
haf/ext/resource/report/base_app.html
haf/ext/resource/report/base_email.html
haf/ext/resource/report/css/bootstrap.min.css
haf/ext/resource/report/css/bootstrap.min.css.map
haf/ext/resource/report/js/base.js
haf/ext/resource/report/js/bootstrap.min.js
haf/ext/resource/report/js/bootstrap.min.js.map
haf/ext/resource/report/js/echarts.min.js
haf/ext/resource/report/js/jquery.min.js
haf/ext/webserver/__init__.py
haf/ext/webserver/app.py
haf/ext/webserver/resources.py
haf-2.9.7.dist-info/METADATA
haf-2.9.7.dist-info/RECORD
haf-2.9.7.dist-info/WHEEL
haf-2.9.7.dist-info/top_level.txt
