Metadata-Version: 2.1
Name: haf
Version: 2.9.7
Summary: UNKNOWN
Home-page: http://github.com/tsbxmw/haf
Author: wei.meng
Author-email: mengwei1101@hotmail.com
License: UNKNOWN
Platform: Posix; MacOS X; Windows
Classifier: Development Status :: 5 - Production/Stable
Classifier: Intended Audience :: Developers
Classifier: License :: OSI Approved :: MIT License
Classifier: Operating System :: OS Independent
Classifier: Topic :: Software Development :: Libraries
Classifier: Topic :: Software Development :: Libraries :: Python Modules
Classifier: Topic :: Software Development :: Testing
Classifier: Programming Language :: Python
Classifier: Programming Language :: Python :: 3.6
Classifier: Programming Language :: Python :: 3.7
Requires-Python: >=3.6
Requires-Dist: requests
Requires-Dist: openpyxl
Requires-Dist: pymysql
Requires-Dist: redis
Requires-Dist: twine
Requires-Dist: assertpy
Requires-Dist: flask
Requires-Dist: flask-restful
Requires-Dist: jinja2
Requires-Dist: pyaml
Requires-Dist: deepdiff
Requires-Dist: setuptools
Requires-Dist: hafapiserver
Requires-Dist: hafsqlpublish
Requires-Dist: jsonschema
Requires-Dist: pluggy
Requires-Dist: progress
